Metadata-Version: 2.1
Name: yrouter-websockets
Version: 0.2
Summary: URL routing for the websockets library.
Home-page: https://github.com/tijani-dia/yrouter-websockets/
Author: Tidiane Dia
Author-email: tidiane.dia@therookiecoder.com
License: BSD-3-Clause
Project-URL: Source, https://github.com/tijani-dia/yrouter-websockets/
Project-URL: Issue tracker, https://github.com/tijani-dia/yrouter-websockets/issues/
Platform: UNKNOWN
Classifier: Development Status :: 3 - Alpha
Classifier: Environment :: Web Environment
Classifier: Intended Audience :: Developers
Classifier: License :: OSI Approved :: BSD License
Classifier: Programming Language :: Python :: 3
Classifier: Programming Language :: Python :: 3 :: Only
Classifier: Programming Language :: Python :: 3.9
Classifier: Programming Language :: Python :: 3.10
Classifier: Topic :: Internet :: WWW/HTTP
Requires-Python: >=3.9
Provides-Extra: test
Provides-Extra: build
License-File: LICENSE
